conflictPackage/_init_.py
conflictPackage/function.py
conflictPacketForLab2-0.1.dist-info/METADATA
conflictPacketForLab2-0.1.dist-info/WHEEL
conflictPacketForLab2-0.1.dist-info/top_level.txt
conflictPacketForLab2-0.1.dist-info/RECORD
