Metadata-Version: 2.1
Name: conflictPacketForLab2
Version: 0.1
Summary: Conflict package for lab2 task1
Home-page: UNKNOWN
Author: UNKNOWN
Author-email: UNKNOWN
License: UNKNOWN
Platform: UNKNOWN
Requires-Dist: pandas (<0.23)
